vi3o-0.11.3.dist-info/METADATA
vi3o-0.11.3.dist-info/top_level.txt
vi3o-0.11.3.dist-info/WHEEL
vi3o-0.11.3.dist-info/RECORD
vi3o-0.11.3.dist-info/LICENSE
vi3o/ffprobe.py
vi3o/cat.py
vi3o/compat.py
vi3o/netcam.py
vi3o/cvview.py
vi3o/sync.py
vi3o/image.py
vi3o/utils.py
vi3o/recording.py
vi3o/debugview.py
vi3o/__init__.py
vi3o/mkv.py
vi3o/imageio.py
vi3o/mjpg.py
vi3o/version.py
vi3o/opencv.py
vi3o/_mkv.abi3.so
vi3o/_mjpg.abi3.so
vi3o.libs/libcairo-2992179a.so.2.11400.8
vi3o.libs/libvorbis-86113e64.so.0.4.8
vi3o.libs/libx265-51947861.so.95
vi3o.libs/liblzma-9c0610aa.so.5.2.2
vi3o.libs/libswresample-8f829c8f.so.2.3.100
vi3o.libs/libnuma-c8473f23.so.1.0.0
vi3o.libs/libwebp-eae543e3.so.6.0.2
vi3o.libs/libopus-37a3229e.so.0.5.3
vi3o.libs/libgsm-aa736f52.so.1.0.12
vi3o.libs/libxcb-shm-5702672e.so.0.0.0
vi3o.libs/libxcb-ffedb2d4.so.1.1.0
vi3o.libs/libogg-b6ceea65.so.0.8.2
vi3o.libs/libXdmcp-911ecd1c.so.6.0.0
vi3o.libs/libsnappy-1125e350.so.1.3.0
vi3o.libs/libxvidcore-a773eded.so.4.3
vi3o.libs/libva-0f7a824e.so.1.3904.0
vi3o.libs/libvorbisenc-93aef8ee.so.2.0.11
vi3o.libs/libpixman-1-7369dbb3.so.0.34.0
vi3o.libs/libxcb-render-f7692d1d.so.0.0.0
vi3o.libs/libjpeg-183425db.so.62.2.0
vi3o.libs/libtheoraenc-b508ccf1.so.1.1.2
vi3o.libs/libXfixes-af4baa9b.so.3.1.0
vi3o.libs/libbsd-4a4ec721.so.0.8.3
vi3o.libs/libspeex-6f258c6c.so.1.5.0
vi3o.libs/libavutil-e4f17c79.so.55.34.101
vi3o.libs/libva-x11-d220c497.so.1.3904.0
vi3o.libs/libXau-6ab8808d.so.6.0.0
vi3o.libs/libzvbi-2db02ce4.so.0.13.2
vi3o.libs/libavcodec-0ff1f37e.so.57.64.101
vi3o.libs/libswscale-0f747626.so.4.2.100
vi3o.libs/libfontconfig-e9a06300.so.1.8.0
vi3o.libs/libfreetype-851758a3.so.6.12.3
vi3o.libs/libdrm-528998a2.so.2.4.0
vi3o.libs/libgomp-ce6cf6a9.so.1.0.0
vi3o.libs/libshine-b48eced9.so.3.0.1
vi3o.libs/libtheoradec-02a81176.so.1.1.4
vi3o.libs/libwavpack-0b19dabd.so.1.2.0
vi3o.libs/libwebpmux-0c81bfce.so.2.0.2
vi3o.libs/libpng16-121b9de7.so.16.28.0
vi3o.libs/libcrystalhd-e4ea0de0.so.3.6
vi3o.libs/libtwolame-6fcc2d32.so.0.0.0
vi3o.libs/libsoxr-e0d4d3e4.so.0.1.1
vi3o.libs/libmp3lame-249ae4b0.so.0.0.0
