Metadata-Version: 2.1
Name: vi3o
Version: 0.11.3
Summary: VIdeo and Image IO
Home-page: http://vi3o.readthedocs.org
Author: Hakan Ardo
Author-email: hakan@debian.org
License: MIT
License-File: LICENSE
Requires-Dist: cffi (>=1.0.0)
Requires-Dist: numpy (>=1.7.1)
Provides-Extra: full
Requires-Dist: pillow (<7) ; extra == 'full'
Requires-Dist: pyglet (<1.5) ; extra == 'full'
